django_rad/__init__.py
django_rad/apps.py
django_rad/discovery.py
django_rad/enums.py
django_rad/exceptions.py
django_rad/models.py
django_rad/permissions.py
django_rad/serializers.py
django_rad/settings.py
django_rad/throttling.py
django_rad/views.py
django_rad/authentication/__init__.py
django_rad/authentication/base.py
django_rad/authentication/decorators.py
django_rad/authentication/session.py
django_rad/authentication/token.py
django_rad/controllers/__init__.py
django_rad/controllers/controllers.py
django_rad/controllers/mixins.py
django_rad/management/commands/__init__.py
django_rad/management/commands/generate_controller.py
django_rad/management/commands/generate_usersapp.py
django_rad/migrations/__init__.py
django_rad/routers/__init__.py
django_rad/routers/routers.py
django_rad/routers/versoning.py
django_rad-0.1.1.dist-info/METADATA
django_rad-0.1.1.dist-info/WHEEL
django_rad-0.1.1.dist-info/top_level.txt
django_rad-0.1.1.dist-info/RECORD
