Metadata-Version: 2.4
Name: django-rad
Version: 0.1.1
Summary: Controller Based Hybrid of DRF and Django Ninja
Author-email: Siddhartha Khanal <sidkhanal99@gmail.com>
Project-URL: Homepage, https://github.com/buffmomoeveryday/django-rad
Classifier: Environment :: Web Environment
Classifier: Framework :: Django
Classifier: Framework :: Django :: 5.2
Classifier: Intended Audience :: Developers
Classifier: License :: OSI Approved :: BSD License
Classifier: Operating System :: OS Independent
Classifier: Programming Language :: Python
Classifier: Programming Language :: Python :: 3
Classifier: Programming Language :: Python :: 3 :: Only
Classifier: Programming Language :: Python :: 3.10
Classifier: Programming Language :: Python :: 3.11
Classifier: Programming Language :: Python :: 3.12
Classifier: Programming Language :: Python :: 3.13
Classifier: Topic :: Internet :: WWW/HTTP
Classifier: Topic :: Internet :: WWW/HTTP :: Dynamic Content
Requires-Python: >=3.12
Requires-Dist: pyjwt>=2.10.1
Requires-Dist: pydantic>=2.11.9
Requires-Dist: django-filter>=25.1
